mlflowcli/__init__.py
mlflowcli/cli.py
mlflowcli/common.py
mlflowcli/mlflow_base.py
mlflowcli/upload_artifact.py
mlflowcli-0.0.2.dist-info/METADATA
mlflowcli-0.0.2.dist-info/WHEEL
mlflowcli-0.0.2.dist-info/entry_points.txt
mlflowcli-0.0.2.dist-info/RECORD
