Metadata-Version: 2.4
Name: mlflowcli
Version: 0.0.2
Summary: AI-powered Git analysis tool using Gemini AI
Project-URL: Documentation, https://github.com/mlflowcli/mlflowcli#readme
Project-URL: Issues, https://github.com/mlflowcli/mlflowcli/issues
Author: MLFlow CLI Contributors
Classifier: Development Status :: 4 - Beta
Classifier: Environment :: Console
Classifier: Intended Audience :: Developers
Classifier: License :: OSI Approved :: MIT License
Classifier: Programming Language :: Python :: 3.9
Classifier: Topic :: Software Development :: Version Control :: Git
Requires-Python: >=3.8
Requires-Dist: click~=8.1.8
Requires-Dist: loguru~=0.7.0
Requires-Dist: mlflow==2.13.0
